LICENSE
README.md
setup.py
crawler_rocket/__init__.py
crawler_rocket/crawler_rocket.py
crawler_rocket/crawler_writer.py
crawler_rocket/logger.py
crawler_rocket/scheduler.py
crawler_rocket.egg-info/PKG-INFO
crawler_rocket.egg-info/SOURCES.txt
crawler_rocket.egg-info/dependency_links.txt
crawler_rocket.egg-info/requires.txt
crawler_rocket.egg-info/top_level.txt
tests/__init__.py
tests/test_crawler_writer.py
tests/test_logger.py
tests/test_scheduler.py