Metadata-Version: 2.1
Name: crawler-rocket
Version: 0.1.0
Summary: Help you to build web crawlers easily and quickly
Home-page: https://github.com/taoohong/crawler-rocket
Author: TaoHong
License: MIT
Classifier: Programming Language :: Python :: 3
Classifier: License :: OSI Approved :: MIT License
Classifier: Operating System :: OS Independent
License-File: LICENSE
